{
    "client": {
        "directory": "client/",
        "run": [
            {
                "linux": [
                    "npm run dev"
                ],
                "windows": [
                    "npm run dev"
                ]
            }
        ],
        "build": [
            {
                "linux": [
                    "npm run build"
                ],
                "windows": [
                    "npm run build"
                ]
            }
        ],
        "install": [
            {
                "linux": [
                    "npm install"
                ],
                "windows": [
                    "npm install"
                ]
            }
        ],
        "test": [
            {
                "linux": [
                    "npm test"
                ],
                "windows": [
                    "npm test"
                ]
            }
        ],
        "start": [
            {
                "linux": [
                    "npm run start"
                ],
                "windows": [
                    "npm run start"
                ]
            }
        ],
        "update": [
            {
                "linux": [
                    "npm update"
                ],
                "windows": [
                    "npm update"
                ]
            }
        ]
    },
    "web-test": {
        "directory": "web-test/",
        "run": [
            {
                "linux": [
                    "npm run dev"
                ],
                "windows": [
                    "npm run dev"
                ]
            }
        ],
        "build": [
            {
                "linux": [
                    "npm run build"
                ],
                "windows": [
                    "npm run build"
                ]
            }
        ],
        "install": [
            {
                "linux": [
                    "npm install"
                ],
                "windows": [
                    "npm install"
                ]
            }
        ],
        "test": [
            {
                "linux": [
                    "npm test"
                ],
                "windows": [
                    "npm test"
                ]
            }
        ],
        "start": [
            {
                "linux": [
                    "npm run start"
                ],
                "windows": [
                    "npm run start"
                ]
            }
        ],
        "update": [
            {
                "linux": [
                    "npm update"
                ],
                "windows": [
                    "npm update"
                ]
            }
        ]
    },
    "python-test": {
        "directory": "python-test/",
        "run": [
            {
                "linux": [
                    "python test.py"
                ],
                "windows": [
                    "python test.py"
                ]
            }
        ],
        "build": [],
        "install": [
            {
                "linux": [
                    "python -m venv venv",
                    "pip install --upgrade pip",
                    "source venv/bin/activate",
                    "pip install -r requirements.txt",
                    "deactivate"
                ],
                "windows": [
                    "python -m venv venv",
                    "pip install --upgrade pip",
                    "venv\\Scripts\\activate",
                    "pip install -r requirements.txt",
                    "deactivate"
                ]
            }
        ],
        "test": [],
        "start": [
            {
                "linux": [
                    "python test.py"
                ],
                "windows": [
                    "python test.py"
                ]
            }
        ],
        "update": [
            {
                "linux": [
                    "source venv/bin/activate",
                    "pip freeze > requirements.txt",
                    "pip install --upgrade pip",
                    "deactivate"
                ],
                "windows": [
                    "venv\\Scripts\\activate",
                    "pip freeze > requirements.txt",
                    "pip install --upgrade pip",
                    "deactivate"
                ]
            }
        ]
    }
}